{
  "version": "1.0",
  "name": "Demo Playlist",
  "description": "A demonstration playlist with various content types",
  "created_at": "2025-01-13T10:00:00Z",
  "modified_at": "2025-01-13T10:00:00Z",
  "auto_repeat": true,
  "shuffle": false,
  "items": [
    {
      "id": "demo-1",
      "name": "Rainbow Cycle Effect",
      "type": "effect",
      "effect_config": {
        "effect_id": "rainbow_cycle",
        "parameters": {
          "speed": 1.0,
          "brightness": 1.0,
          "hue_shift": 0.0
        }
      },
      "duration": 30.0,
      "order": 0,
      "transition_in": {
        "type": "fade",
        "parameters": {"duration": 1.0}
      },
      "transition_out": {
        "type": "fade",
        "parameters": {"duration": 1.0}
      }
    },
    {
      "id": "demo-2",
      "name": "Welcome Message",
      "type": "text",
      "file_path": "{\"text\":\"Welcome to Prismatron!\",\"font_family\":\"DejaVu Sans\",\"font_style\":\"normal\",\"font_size\":\"auto\",\"fg_color\":\"#00FFFF\",\"bg_color\":\"#000000\",\"animation\":\"static\",\"alignment\":\"center\",\"vertical_alignment\":\"center\",\"duration\":10.0,\"fps\":30.0}",
      "duration": 10.0,
      "order": 1,
      "transition_in": {
        "type": "ledfade",
        "parameters": {"duration": 0.5}
      },
      "transition_out": {
        "type": "ledfade",
        "parameters": {"duration": 0.5}
      }
    },
    {
      "id": "demo-3",
      "name": "Color Wave Effect",
      "type": "effect",
      "effect_config": {
        "effect_id": "color_wave",
        "parameters": {
          "color": "#ff0066",
          "speed": 2.0,
          "wavelength": 100
        }
      },
      "duration": 20.0,
      "order": 2,
      "transition_in": {
        "type": "none",
        "parameters": {}
      },
      "transition_out": {
        "type": "blur",
        "parameters": {}
      }
    }
  ]
}
